feature_selector/__init__.py
feature_selector/feature_selector.py
feature_selector-1.0.0.dist-info/LICENSE
feature_selector-1.0.0.dist-info/METADATA
feature_selector-1.0.0.dist-info/WHEEL
feature_selector-1.0.0.dist-info/top_level.txt
feature_selector-1.0.0.dist-info/RECORD
