Metadata-Version: 2.1
Name: feature-selector
Version: 1.0.0
Summary: FeatureSelector is a class for removing features for a dataset intended for machine learning
Home-page: https://github.com/Jie-Yuan/FeatureSelector
Author: JieYuan
Author-email: 313303303@qq.com
Maintainer: JieYuan
Maintainer-email: 313303303@qq.com
License: MIT
Keywords: 特征选择,Feature Selector,Feature
Platform: all
Classifier: Development Status :: 4 - Beta
Classifier: Operating System :: OS Independent
Classifier: Intended Audience :: Developers
Classifier: License :: OSI Approved :: MIT License
Classifier: Programming Language :: Python
Classifier: Programming Language :: Python :: Implementation
Classifier: Programming Language :: Python :: 3.5
Classifier: Topic :: Software Development :: Libraries
Requires-Python: >=3.5
Requires-Dist: lightgbm (==2.1.1)
Requires-Dist: matplotlib (==2.1.2)
Requires-Dist: seaborn (==0.8.1)
Requires-Dist: numpy (==1.14.5)
Requires-Dist: pandas (==0.23.1)
Requires-Dist: scikit-learn (==0.19.1)
